AUTHORS.rst
CONTRIBUTING.rst
HISTORY.rst
LICENSE
MANIFEST.in
README.rst
setup.cfg
setup.py
django_statuspage.egg-info/PKG-INFO
django_statuspage.egg-info/SOURCES.txt
django_statuspage.egg-info/dependency_links.txt
django_statuspage.egg-info/not-zip-safe
django_statuspage.egg-info/pbr.json
django_statuspage.egg-info/top_level.txt
djstatuspage/__init__.py
djstatuspage/models.py
djstatuspage/views.py