Metadata-Version: 1.1
Name: django-statuspage
Version: 0.1.0
Summary: Your project description goes here
Home-page: https://github.com/redfunction/django-statuspage
Author: Django Statuspage
Author-email: margus.laak@redfunction.ee
License: BSD
Keywords: django-statuspage
Platform: UNKNOWN
Classifier: Development Status :: 3 - Alpha
Classifier: Framework :: Django
Classifier: Intended Audience :: Developers
Classifier: License :: OSI Approved :: BSD License
Classifier: Natural Language :: English
Classifier: Programming Language :: Python :: 2
Classifier: Programming Language :: Python :: 2.7
Classifier: Programming Language :: Python :: 3
Classifier: Programming Language :: Python :: 3.3
Classifier: Programming Language :: Python :: 3.4
